mlflow_assist/__init__.py
mlflow_assist/templates/basic/.gitignore
mlflow_assist/templates/basic/README.md
mlflow_assist/templates/basic/requirements.txt
mlflow_assist/templates/basic/config/config.yaml
mlflow_assist/templates/basic/src/data/load_data.py
mlflow_assist/templates/basic/src/models/train_model.py
mlflow_assist/templates/basic/src/utils/config.py
mlflow_assist-0.2.0.dist-info/licenses/LICENSE
mlflow_assist-0.2.0.dist-info/METADATA
mlflow_assist-0.2.0.dist-info/WHEEL
mlflow_assist-0.2.0.dist-info/entry_points.txt
mlflow_assist-0.2.0.dist-info/top_level.txt
mlflow_assist-0.2.0.dist-info/RECORD
