Metadata-Version: 2.4
Name: mlflow-assist
Version: 0.2.0
Summary: A comprehensive toolkit for ML and LLM development
Home-page: https://github.com/happyvibess/mlflow-assist
Author: happyvibess
Author-email: MLFlow-Assist Team <support@mlflow-assist.dev>
License: MIT
Project-URL: Documentation, https://github.com/happyvibess/mlflow-assist/tree/master/docs
Project-URL: Bug Reports, https://github.com/happyvibess/mlflow-assist/issues
Project-URL: Source Code, https://github.com/happyvibess/mlflow-assist
Project-URL: Buy me a coffee, https://www.buymeacoffee.com/happyvibess
Keywords: machine-learning,deep-learning,llm,mlops,automl,gpt,model-optimization,mlflow,enterprise-ai,ai-automation,model-monitoring,deployment,pytorch,tensorflow,prompt-engineering
Classifier: Development Status :: 4 - Beta
Classifier: Intended Audience :: Developers
Classifier: Intended Audience :: Science/Research
Classifier: Intended Audience :: Information Technology
Classifier: Topic :: Scientific/Engineering :: Artificial Intelligence
Classifier: Topic :: Software Development :: Libraries :: Python Modules
Classifier: Topic :: Software Development :: Build Tools
Classifier: Topic :: System :: Monitoring
Classifier: Environment :: Console
Classifier: Natural Language :: English
Classifier: Operating System :: OS Independent
Classifier: Programming Language :: Python :: 3
Classifier: Programming Language :: Python :: 3.8
Classifier: Programming Language :: Python :: 3.9
Classifier: Programming Language :: Python :: 3.10
Classifier: Programming Language :: Python :: 3.11
Requires-Python: >=3.8
License-File: LICENSE
Requires-Dist: numpy>=1.21.0
Requires-Dist: pandas>=1.3.0
Requires-Dist: scikit-learn>=1.0.0
Requires-Dist: torch>=1.9.0
Requires-Dist: transformers>=4.20.0
Requires-Dist: mlflow>=1.20.0
Requires-Dist: click>=8.0.0
Requires-Dist: rich>=10.0.0
Requires-Dist: typer>=0.4.0
Requires-Dist: pydantic>=1.8.0
Requires-Dist: python-dotenv>=0.19.0
Provides-Extra: dev
Requires-Dist: pytest>=6.0.0; extra == "dev"
Requires-Dist: black>=21.0.0; extra == "dev"
Requires-Dist: isort>=5.0.0; extra == "dev"
Requires-Dist: flake8>=3.9.0; extra == "dev"
Requires-Dist: mypy>=0.910; extra == "dev"
Dynamic: author
Dynamic: home-page
Dynamic: license-file
Dynamic: requires-python
